Workbook

Sheet SN
A1: 1000035 | B1: SIMPLES NACIONAL
A2: 1000053 | B2: SIMPLES NACIONAL
A3: 1000060 | B3: SIMPLES NACIONAL
A4: 1000064 | B4: SIMPLES NACIONAL
A5: 1000089 | B5: SIMPLES NACIONAL
A6: 1000105 | B6: SIMPLES NACIONAL
A7: 1000187 | B7: SIMPLES NACIONAL
A8: 1000199 | B8: SIMPLES NACIONAL
A9: 1000205 | B9: SIMPLES NACIONAL
A10: 1000219 | B10: SIMPLES NACIONAL
A11: 1000237 | B11: SIMPLES NACIONAL
A12: 1000242 | B12: SIMPLES NACIONAL
... A202: 1004147 | B202: SIMPLES NACIONAL

Sheet Exportação SAPUI5
A1: Parceiro de negócios | B1: ID FORNECEDOR | C1: Critério de pesquisa 1 | D1: Critério de pesquisa 2 | E1: SIMPLES NACIONAL
A2: Instituto Renal E Multiclinica de Servic os Medicos Hospitalares Ltda (1000002) | B2: 1000002 | C2: 43808742000150 | D2: INSTITUTO DO RIM E T | E2: =VLOOKUP(B2,SN!A:B,2,0) -> #N/A
A3: Medvida Atividades Medicas Ltda (1000003) | B3: 1000003 | C3: 49159260000101 | D3: MEDVIDA ATIVIDADES M | E3: =VLOOKUP(B3,SN!A:B,2,0) -> #N/A
A4: Kataoka Prestacao de Servicos Medicos E Psicologicos Ltda (1000004) | B4: 1000004 | C4: 31700532000165 | D4: KATAOKA PRESTACAO DE | E4: =VLOOKUP(B4,SN!A:B,2,0) -> #N/A
A5: Ab Vitae Servicos Medicos S/s (1000005) | B5: 1000005 | C5: 25315871000125 | D5: AB VITAE SERVICOS ME | E5: =VLOOKUP(B5,SN!A:B,2,0) -> #N/A
A6: Instituto Clinico Gomes Ltda (1000006) | B6: 1000006 | C6: 45776776000136 | D6: INSTITUTO CLINICO GO | E6: =VLOOKUP(B6,SN!A:B,2,0) -> #N/A
A7: Ribeiro & Toledo - Materiais de Construc ao Ltda (1000007) | B7: 1000007 | C7: 11444561000104 | D7: CENTRAL DE COMPRAS | E7: =VLOOKUP(B7,SN!A:B,2,0) -> #N/A
A8: Instituto de Flebologia de Sao Luis Ltda (1000008) | B8: 1000008 | C8: 35956399000163 | D8: INSTITUTO DE FLEBOLO | E8: =VLOOKUP(B8,SN!A:B,2,0) -> #N/A
A9: Modestolima Ltda (1000009) | B9: 1000009 | C9: 48947039000147 | D9: MODESTO LIMA | E9: =VLOOKUP(B9,SN!A:B,2,0) -> #N/A
A10: Plus Med - Sociedade Medica Ltda (1000010) | B10: 1000010 | C10: 21832827000131 | D10: PLUS MED - SOCIEDADE | E10: =VLOOKUP(B10,SN!A:B,2,0) -> #N/A
A11: Irmaos Goncalves Comercio E Industria Lt da. (1000011) | B11: 1000011 | C11: 04082624003929 | D11: SUPERMERCADO IRMAOS | E11: =VLOOKUP(B11,SN!A:B,2,0) -> #N/A
A12: Js Nordeste Medica E Consultoria Ltda (1000012) | B12: 1000012 | C12: 32813516000141 | D12: JS NORDESTE MEDICA E | E12: =VLOOKUP(B12,SN!A:B,2,0) -> #N/A
A13: Cm Hospitalar S.a. (1000013) | B13: 1000013 | C13: 12420164000580 | D13: MAFRA HOSPITALAR | E13: =VLOOKUP(B13,SN!A:B,2,0) -> #N/A
... A3718: EDUARDA ALMEIDA DE SOUZA (1007143) | B3718: 1007143 | C3718: 15929989761 | D3718: EDUARDA ALMEIDA DE S | E3718: =VLOOKUP(B3718,SN!A:B,2,0) -> #N/A
A3719: Hospital Santa Helena Sociedade Anônima (BR) | C3719: 06033403000113 | D3719: HOSPITAL SANTA HELEN | E3719: =VLOOKUP(B3719,SN!A:B,2,0) -> #N/A
